{
    "id": "au-16.3",
    "class": "SP800-53-enhancement",
    "title": "Disassociability",
    "parameters": [
        {
            "id": "au-16.3_prm_1",
            "label": "organization-defined measures"
        }
    ],
    "properties": [
        {
            "name": "label",
            "value": "AU-16(3)"
        },
        {
            "name": "sort-id",
            "value": "AU-16(03)"
        }
    ],
    "parts": [
        {
            "id": "au-16.3_smt",
            "name": "statement",
            "prose": "Implement {{ au-16.3_prm_1 }} to disassociate individuals from audit information transmitted across organizational boundaries."
        },
        {
            "id": "au-16.3_gdn",
            "name": "guidance",
            "prose": "Preserving identities in audit trails could have privacy ramifications, such as enabling the tracking and profiling of individuals, but may not be operationally necessary. These risks could be further amplified when transmitting information across organizational boundaries. Implementing privacy-enhancing cryptographic techniques can disassociate individuals from audit information and reduce privacy risk while maintaining accountability."
        }
    ],
    "group_title": "Audit and Accountability"
}