{
    "id": "ir-4.7",
    "class": "SP800-53-enhancement",
    "title": "Insider Threats \u2014 Intra-organization Coordination",
    "parameters": [
        {
            "id": "ir-4.7_prm_1",
            "label": "organization-defined entities"
        }
    ],
    "properties": [
        {
            "name": "label",
            "value": "IR-4(7)"
        },
        {
            "name": "sort-id",
            "value": "IR-04(07)"
        }
    ],
    "parts": [
        {
            "id": "ir-4.7_smt",
            "name": "statement",
            "prose": "Coordinate an incident handling capability for insider threats that includes the following organizational entities {{ ir-4.7_prm_1 }}."
        },
        {
            "id": "ir-4.7_gdn",
            "name": "guidance",
            "prose": "Incident handling for insider threat incidents (e.g., preparation, detection and analysis, containment, eradication, and recovery) requires coordination among many organizational entities, including mission or business owners, system owners, human resources offices, procurement offices, personnel offices, physical security offices, senior agency information security officer, operations personnel, risk executive (function), senior agency official for privacy, and legal counsel. In addition, organizations may require external support from federal, state, and local law enforcement agencies."
        }
    ],
    "group_title": "Incident Response"
}