{
    "id": "ir-4.4",
    "class": "SP800-53-enhancement",
    "title": "Information Correlation",
    "properties": [
        {
            "name": "label",
            "value": "IR-4(4)"
        },
        {
            "name": "sort-id",
            "value": "IR-04(04)"
        }
    ],
    "parts": [
        {
            "id": "ir-4.4_smt",
            "name": "statement",
            "prose": "Correlate incident information and individual incident responses to achieve an organization-wide perspective on incident awareness and response."
        },
        {
            "id": "ir-4.4_gdn",
            "name": "guidance",
            "prose": "Sometimes, a threat event, such as a hostile cyber-attack, can only be observed by bringing together information from different sources, including various reports and reporting procedures established by organizations."
        }
    ],
    "group_title": "Incident Response"
}