{
    "id": "pe-10",
    "class": "SP800-53",
    "title": "Emergency Shutoff",
    "parameters": [
        {
            "id": "pe-10_prm_1",
            "label": "organization-defined system or individual system components"
        },
        {
            "id": "pe-10_prm_2",
            "label": "organization-defined location by system or system component"
        }
    ],
    "properties": [
        {
            "name": "label",
            "value": "PE-10"
        },
        {
            "name": "sort-id",
            "value": "PE-10"
        }
    ],
    "links": [
        {
            "href": "#pe-15",
            "rel": "related",
            "text": "PE-15"
        }
    ],
    "parts": [
        {
            "id": "pe-10_smt",
            "name": "statement",
            "parts": [
                {
                    "id": "pe-10_smt.a",
                    "name": "item",
                    "properties": [
                        {
                            "name": "label",
                            "value": "a."
                        }
                    ],
                    "prose": "Provide the capability of shutting off power to {{ pe-10_prm_1 }} in emergency situations;"
                },
                {
                    "id": "pe-10_smt.b",
                    "name": "item",
                    "properties": [
                        {
                            "name": "label",
                            "value": "b."
                        }
                    ],
                    "prose": "Place emergency shutoff switches or devices in {{ pe-10_prm_2 }} to facilitate access for authorized personnel; and"
                },
                {
                    "id": "pe-10_smt.c",
                    "name": "item",
                    "properties": [
                        {
                            "name": "label",
                            "value": "c."
                        }
                    ],
                    "prose": "Protect emergency power shutoff capability from unauthorized activation."
                }
            ]
        },
        {
            "id": "pe-10_gdn",
            "name": "guidance",
            "prose": "Emergency power shutoff primarily applies to organizational facilities that contain concentrations of system resources, including data centers, mainframe computer rooms, server rooms, and areas with computer-controlled machinery."
        }
    ],
    "controls": [
        {
            "id": "pe-10.1",
            "class": "SP800-53-enhancement",
            "title": "Accidental and Unauthorized Activation",
            "properties": [
                {
                    "name": "label",
                    "value": "PE-10(1)"
                },
                {
                    "name": "status",
                    "value": "Withdrawn"
                },
                {
                    "name": "sort-id",
                    "value": "PE-10(01)"
                }
            ],
            "links": [
                {
                    "href": "#pe-10",
                    "rel": "incorporated-into",
                    "text": "PE-10"
                }
            ]
        }
    ],
    "group_title": "Physical and Environmental Protection"
}